science/__init__.py
science/shapes.py
science/units.py
tools/__init__.py
tools/dataList_conversion.py
tools/decorators.py
tools/jurisdiction.py
tools/ptime.py
tools/pydebugger.py
tools/tag.py
tools/operators/__init__.py
tools/operators/comparison.py
tools/operators/matical.py
tools/variables/__init__.py
tools/variables/encrypt.py
tools/variables/share.py
tools/variables/tmp.py
xystudio_all-1.4.4.dist-info/licenses/LICENSE
xystudio_all-1.4.4.dist-info/METADATA
xystudio_all-1.4.4.dist-info/WHEEL
xystudio_all-1.4.4.dist-info/top_level.txt
xystudio_all-1.4.4.dist-info/RECORD
