Metadata-Version: 2.4
Name: xystudio-all
Version: 1.4.4
Summary: Xystudio all packages.
Home-page: https://github.com/xystudio889/xystudio-all
Author: xystudio
Author-email: 173288240@qq.com
License: MIT
Requires-Python: >=3.8
License-File: LICENSE
Dynamic: author
Dynamic: author-email
Dynamic: description
Dynamic: home-page
Dynamic: license
Dynamic: license-file
Dynamic: requires-python
Dynamic: summary
